popsink_transformer/__init__.py
popsink_transformer/avro_to_json/__init__.py
popsink_transformer/avro_to_json/main.py
popsink_transformer/avro_to_sql/__init__.py
popsink_transformer/avro_to_sql/main.py
popsink_transformer/avro_to_sql/utils/__init__.py
popsink_transformer/avro_to_sql/utils/type_converter.py
popsink_transformer/errors.py
popsink_transformer/transformer.py
popsink_transformer-2.3.3.dist-info/METADATA
popsink_transformer-2.3.3.dist-info/WHEEL
popsink_transformer-2.3.3.dist-info/RECORD
