Metadata-Version: 2.1
Name: popsink-transformer
Version: 2.3.3
Summary: Popsink transformer
Author: Popsink
Author-email: contact@popsink.com
Requires-Python: >=3.10,<4.0
Classifier: Programming Language :: Python :: 3
Classifier: Programming Language :: Python :: 3.10
Classifier: Programming Language :: Python :: 3.11
Classifier: Programming Language :: Python :: 3.12
